Metadata-Version: 1.2
Name: quoterz
Version: 0.0.1.dev1
Summary: Quotes taking assistant
Home-page: https://github.com/adiping1
Author: Aditya Pingle
Author-email: adiping1@umbc.edu
License: MIT
Project-URL: Funding, https://github.com/adiping1/funds
Project-URL: Bug Reports, https://github.com/adiping1/bugs
Project-URL: Say Thanks!, https://github.com/adiping1/thanks
Project-URL: Source, https://github.com/adiping1/src
Keywords: sample aditya piper
Platform: UNKNOWN
Classifier: Development Status :: 3 - Alpha
Classifier: Intended Audience :: Developers
Classifier: Topic :: Software Development :: Build Tools
Classifier: License :: OSI Approved :: MIT License
Classifier: Programming Language :: Python :: 2.7
